MANIFEST.in
README.md
requirements.txt
setup.cfg
setup.py
rex_gym/__init__.py
rex_gym.egg-info/PKG-INFO
rex_gym.egg-info/SOURCES.txt
rex_gym.egg-info/dependency_links.txt
rex_gym.egg-info/entry_points.txt
rex_gym.egg-info/requires.txt
rex_gym.egg-info/top_level.txt
rex_gym/agents/__init__.py
rex_gym/agents/ppo/__init__.py
rex_gym/agents/ppo/algorithm.py
rex_gym/agents/ppo/memory.py
rex_gym/agents/ppo/normalize.py
rex_gym/agents/ppo/simple_ppo_agent.py
rex_gym/agents/ppo/utility.py
rex_gym/agents/scripts/__init__.py
rex_gym/agents/scripts/configs.py
rex_gym/agents/scripts/networks.py
rex_gym/agents/scripts/utility.py
rex_gym/agents/tools/__init__.py
rex_gym/agents/tools/attr_dict.py
rex_gym/agents/tools/batch_env.py
rex_gym/agents/tools/count_weights.py
rex_gym/agents/tools/in_graph_batch_env.py
rex_gym/agents/tools/in_graph_env.py
rex_gym/agents/tools/loop.py
rex_gym/agents/tools/mock_algorithm.py
rex_gym/agents/tools/mock_environment.py
rex_gym/agents/tools/simulate.py
rex_gym/agents/tools/streaming_mean.py
rex_gym/agents/tools/wrappers.py
rex_gym/cli/__init__.py
rex_gym/cli/entry_point.py
rex_gym/envs/__init__.py
rex_gym/envs/rex_gym_env.py
rex_gym/envs/gym/__init__.py
rex_gym/envs/gym/gallop_env.py
rex_gym/envs/gym/go_to_env.py
rex_gym/envs/gym/poses_env.py
rex_gym/envs/gym/rex_recovery_env.py
rex_gym/envs/gym/rex_side_swipe_env.py
rex_gym/envs/gym/standup_env.py
rex_gym/envs/gym/turn_env.py
rex_gym/envs/gym/walk_env.py
rex_gym/model/__init__.py
rex_gym/model/gait_planner.py
rex_gym/model/kinematics.py
rex_gym/model/mark_constants.py
rex_gym/model/motor.py
rex_gym/model/rex.py
rex_gym/model/rex_constants.py
rex_gym/model/terrain.py
rex_gym/playground/__init__.py
rex_gym/playground/policy_player.py
rex_gym/playground/trainer.py
rex_gym/policies/gallop/ik/config.yaml
rex_gym/policies/gallop/ik/model.ckpt-2000000.data-00000-of-00001
rex_gym/policies/gallop/ik/model.ckpt-2000000.index
rex_gym/policies/gallop/ik/model.ckpt-2000000.meta
rex_gym/policies/gallop/ol/config.yaml
rex_gym/policies/gallop/ol/model.ckpt-4000000.data-00000-of-00001
rex_gym/policies/gallop/ol/model.ckpt-4000000.index
rex_gym/policies/gallop/ol/model.ckpt-4000000.meta
