Metadata-Version: 2.1
Name: rex-gym
Version: 0.2.6
Summary: UNKNOWN
Home-page: https://github.com/nicrusso7/rex-gym
Author: Nicola Russo
Author-email: dott.nicolarusso@gmail.com
License: Apache 2.0
Download-URL: https://github.com/nicrusso7/rex-gym/archive/master.zip
Keywords: openai,gym,robot,quadruped,pybullet,ai,reinforcement learning,machine learning,RL,ML,tensorflow,spotmicro,rex
Platform: UNKNOWN
Classifier: Development Status :: 4 - Beta
Classifier: Intended Audience :: Developers
Classifier: Topic :: Scientific/Engineering :: Artificial Intelligence
Classifier: Framework :: Robot Framework :: Library
Classifier: License :: OSI Approved :: Apache Software License
Classifier: Programming Language :: Python :: 3.7
